ducktables/__init__.py
ducktables/aws.py
ducktables/github.py
ducktables/openai.py
ducktables/google/__init__.py
ducktables/google/analytics.py
ducktables-0.1.4.dist-info/METADATA
ducktables-0.1.4.dist-info/WHEEL
ducktables-0.1.4.dist-info/top_level.txt
ducktables-0.1.4.dist-info/RECORD
