Metadata-Version: 2.1
Name: ducktables
Version: 0.1.4
Summary: Python Table Functions for DuckDB
Home-page: UNKNOWN
License: UNKNOWN
Platform: UNKNOWN
Requires-Dist: PyGithub (==1.58.1)
Requires-Dist: boto3 (==1.26.117)
Requires-Dist: google-api-core (==2.11.0)
Requires-Dist: google-api-python-client (==2.86.0)
Requires-Dist: google-auth-httplib2 (==0.1.0)
Requires-Dist: google-auth-oauthlib (==1.0.0)
Requires-Dist: google-auth (==2.17.3)
Requires-Dist: googleapis-common-protos (==1.59.0)
Requires-Dist: gspread (==5.8.0)
Requires-Dist: oauth2client (==4.1.3)
Requires-Dist: openai (==0.27.4)
Requires-Dist: s3transfer (==0.6.0)
